[
    {
        "url":"01",
        "enlace":"https://www.youtube.com/watch?v=0gS9SHYKbNk&list=PL8hEQ3tnSmrQW48TEk0241DeZWTykRYDi"

    },
    {
        "url":"02",
        "enlace":"https://www.youtube.com/watch?v=5ChC3w48amw&list=PL8hEQ3tnSmrQW48TEk0241DeZWTykRYDi&index=2"

    },
    {
        "url":"03",
        "enlace":"https://www.youtube.com/watch?v=24BQyFqN2oA&list=PL8hEQ3tnSmrQW48TEk0241DeZWTykRYDi&index=3"

    },
    {
        "url":"04",
        "enlace":"https://www.youtube.com/watch?v=zBJhsSGMCm4&list=PL8hEQ3tnSmrQW48TEk0241DeZWTykRYDi&index=4"

    },
    {
        "url":"05",
        "enlace":"https://www.youtube.com/watch?v=-OxHsu4gpyQ&list=PL8hEQ3tnSmrQW48TEk0241DeZWTykRYDi&index=5"

    },
    {
        "url":"06",
        "enlace":"https://www.youtube.com/watch?v=cCgSjXcZio4&list=PL8hEQ3tnSmrQW48TEk0241DeZWTykRYDi&index=6"

    },
    {
        "url":"07",
        "enlace":"https://www.youtube.com/watch?v=8WcJQN1XV7U&list=PL8hEQ3tnSmrQW48TEk0241DeZWTykRYDi&index=7"
    },
    {
        "url":"08",
        "enlace":"https://www.youtube.com/watch?v=Q-aCbWq9wcU&list=PL8hEQ3tnSmrQW48TEk0241DeZWTykRYDi&index=8"
    },
    {
        "url":"09",
        "enlace":"https://www.youtube.com/watch?v=CbjW5NNfpoA&list=PL8hEQ3tnSmrQW48TEk0241DeZWTykRYDi&index=9"
    }
]